py_3d_modeler/__init__.py
py_3d_modeler-0.0.1.dist-info/METADATA
py_3d_modeler-0.0.1.dist-info/WHEEL
py_3d_modeler-0.0.1.dist-info/RECORD
