Metadata-Version: 2.1
Name: py-3d-modeler
Version: 0.0.1
Summary: 
Author: Young
Author-email: gooker_young@163.com
Requires-Python: >=3.8,<3.9
Classifier: Programming Language :: Python :: 3
Classifier: Programming Language :: Python :: 3.8
Requires-Dist: jupyter (>=1.0.0,<2.0.0)
Requires-Dist: matplotlib (>=3.7,<3.8)
Requires-Dist: numpy (>=1.24,<1.25)
Requires-Dist: pymesh (>=1.0.2,<2.0.0)
Requires-Dist: scipy (>=1.10,<1.11)
Requires-Dist: vtk (>=9.3.1,<10.0.0)
